sgmdata/__init__.py
sgmdata/config.py
sgmdata/interpolate.py
sgmdata/load.py
sgmdata/search.py
sgmdata/version.py
sgmdata/xrffit.py
sgmdata/plots/__init__.py
sgmdata/plots/eemscan.py
sgmdata/plots/xrfmap.py
sgmdata/plots/callbacks/eemscan/color_palette_1.x.x.js
sgmdata/plots/callbacks/eemscan/color_palette_2.x.x.js
sgmdata/plots/callbacks/eemscan/color_range_1.x.x.js
sgmdata/plots/callbacks/eemscan/color_range_2.x.x.js
sgmdata/plots/callbacks/eemscan/det_select_1.x.x.js
sgmdata/plots/callbacks/eemscan/det_select_2.x.x.js
sgmdata/plots/callbacks/eemscan/download_1.x.x.js
sgmdata/plots/callbacks/eemscan/download_2.x.x.js
sgmdata/plots/callbacks/eemscan/flslider_1.x.x.js
sgmdata/plots/callbacks/eemscan/flslider_2.x.x.js
sgmdata/plots/callbacks/eemscan/reset_1.x.x.js
sgmdata/plots/callbacks/eemscan/reset_2.x.x.js
sgmdata/plots/callbacks/eemscan/select_1.x.x.js
sgmdata/plots/callbacks/eemscan/select_2.x.x.js
sgmdata/plots/callbacks/xrfmap/clipboard_1.x.x.js
sgmdata/plots/callbacks/xrfmap/clipboard_2.x.x.js
sgmdata/plots/callbacks/xrfmap/color_palette_1.x.x.js
sgmdata/plots/callbacks/xrfmap/color_palette_2.x.x.js
sgmdata/plots/callbacks/xrfmap/color_range_1.x.x.js
sgmdata/plots/callbacks/xrfmap/color_range_2.x.x.js
sgmdata/plots/callbacks/xrfmap/delete_row_1.x.x.js
sgmdata/plots/callbacks/xrfmap/delete_row_2.x.x.js
sgmdata/plots/callbacks/xrfmap/det_select_1.x.x.js
sgmdata/plots/callbacks/xrfmap/det_select_2.x.x.js
sgmdata/plots/callbacks/xrfmap/det_select_xyz_1.x.x.js
sgmdata/plots/callbacks/xrfmap/det_select_xyz_2.x.x.js
sgmdata/plots/callbacks/xrfmap/det_sum_select_1.x.x.js
sgmdata/plots/callbacks/xrfmap/det_sum_select_2.x.x.js
sgmdata/plots/callbacks/xrfmap/macro_build_1.x.x.js
sgmdata/plots/callbacks/xrfmap/macro_build_2.x.x.js
sgmdata/plots/callbacks/xrfmap/roi_select_1.x.x.js
sgmdata/plots/callbacks/xrfmap/roi_select_2.x.x.js
sgmdata/sign/__init__.py
sgmdata/sign/baseconv.py
sgmdata/sign/signing.py
sgmdata/sign/util.py
sgmdata/utilities/__init__.py
sgm_data-0.5.0b0.dist-info/LICENSE
sgm_data-0.5.0b0.dist-info/METADATA
sgm_data-0.5.0b0.dist-info/WHEEL
sgm_data-0.5.0b0.dist-info/top_level.txt
sgm_data-0.5.0b0.dist-info/RECORD
