Metadata-Version: 2.1
Name: sgm-data
Version: 0.5.0b0
Summary: Module for loading, interpolating and plotting data taken at the SGM Beamline at the Canadian Light Source.
Home-page: https://github.lightsource.ca/arthurz/sgmdata
Author: Zachary Arthur
Author-email: zachary.arthur@lightsource.ca
License: MIT
Classifier: License :: OSI Approved :: MIT License
Classifier: Programming Language :: Python :: 3
Classifier: Programming Language :: Python :: 3.7
License-File: LICENSE
Requires-Dist: blosc (==1.10.2)
Requires-Dist: lz4 (==3.1.3)
Requires-Dist: dask[complete] (>=2021.03.0)
Requires-Dist: msgpack (==1.0.2)
Requires-Dist: pandas (>=1.1.5)
Requires-Dist: h5py (>=2.10.0)
Requires-Dist: bokeh (>=1.4.0)
Requires-Dist: numpy (>=1.18.3)
Requires-Dist: scipy (>=1.4.1)
Requires-Dist: tqdm
Requires-Dist: python-slugify
Requires-Dist: beautifulsoup4
Requires-Dist: matplotlib
Requires-Dist: requests
Requires-Dist: lmfit
